{"py/object": "state.state.State", "teams": [{"py/object": "state.state.Team", "name": "Team 1", "members": ["136856906139566081"], "board": [{"py/object": "models.graph.GraphNode", "value": {"py/object": "models.tile.Tile", "id": 1, "name": "Lorem ipsum", "description": "dolor sit amet", "state": {"py/reduce": [{"py/type": "models.tile.TileState"}, {"py/tuple": [1]}]}, "required_for_completetion": 2, "requirements": {"Fang": {"py/object": "models.criteria.Count", "threshold": 1, "count": 0}, "Purple Sweets": {"py/object": "models.criteria.Count", "threshold": 100, "count": 0}}}, "neighbors": []}]}, {"py/object": "state.state.Team", "name": "Team 1", "members": ["136856906139566081"], "board": [{"py/object": "models.graph.GraphNode", "value": {"py/object": "models.tile.Tile", "id": 1, "name": "Lorem ipsum", "description": "dolor sit amet", "state": {"py/id": 7}, "required_for_completetion": 2, "requirements": {"Fang": {"py/object": "models.criteria.Count", "threshold": 1, "count": 0}, "Purple Sweets": {"py/object": "models.criteria.Count", "threshold": 100, "count": 0}}}, "neighbors": []}]}]}